asr_screen_shear/__init__.py
asr_screen_shear/client_view.py
asr_screen_shear/dis.py
asr_screen_shear/pc2.py
asr_screen_shear/server.py
asr_screen_shear/server_share.py
asr_screen_shear-2.0.0.dist-info/licenses/LICENSE
asr_screen_shear-2.0.0.dist-info/METADATA
asr_screen_shear-2.0.0.dist-info/WHEEL
asr_screen_shear-2.0.0.dist-info/top_level.txt
asr_screen_shear-2.0.0.dist-info/RECORD
