Metadata-Version: 2.4
Name: asr_screen_shear
Version: 2.0.0
Summary: Screen sharing package with automatic dependencies
Home-page: https://asrbuntu.neocities.org
Author: Aser
Author-email: aserah411@gmail.com
License: MIT
Classifier: Programming Language :: Python :: 3
Classifier: License :: OSI Approved :: MIT License
Requires-Python: >=3.8
License-File: LICENSE
Requires-Dist: pyautogui
Requires-Dist: pillow
Requires-Dist: opencv-python
Requires-Dist: numpy
Dynamic: license-file
